strmprivacy_diagnostics-1.2.2-py3.9-nspkg.pth
strmprivacy/diagnostics/__init__.py
strmprivacy/diagnostics/diagnostics.py
strmprivacy/diagnostics/metrics.py
strmprivacy/diagnostics/plots.py
strmprivacy/diagnostics/report/__init__.py
strmprivacy/diagnostics/report/report.py
strmprivacy_diagnostics-1.2.2.dist-info/METADATA
strmprivacy_diagnostics-1.2.2.dist-info/WHEEL
strmprivacy_diagnostics-1.2.2.dist-info/namespace_packages.txt
strmprivacy_diagnostics-1.2.2.dist-info/top_level.txt
strmprivacy_diagnostics-1.2.2.dist-info/RECORD
