Metadata-Version: 2.1
Name: strmprivacy-diagnostics
Version: 1.2.2
Summary: STRM Privacy Diagnostics for reporting privacy metrics on a dataset.
Home-page: UNKNOWN
Author: Stream Machine B.V.
Author-email: apis@strmprivacy.io
License: UNKNOWN
Keywords: strmprivacy privacy diagnostics
Platform: UNKNOWN
Classifier: Programming Language :: Python :: 3.6
Classifier: Programming Language :: Python :: 3.7
Classifier: Programming Language :: Python :: 3.8
Classifier: Programming Language :: Python :: 3.9
Classifier: Intended Audience :: Developers
Classifier: Operating System :: OS Independent
Requires-Python: >=3.6
Requires-Dist: pandas (>=1.4.3)
Requires-Dist: numpy (>=1.23.2)
Requires-Dist: matplotlib (>=3.5.3)
Requires-Dist: fpdf (>=1.7.2)
Requires-Dist: temp (>=2020.7.2)
Requires-Dist: argparse (>=1.4.0)
Requires-Dist: pathlib (>=1.0.1)
Requires-Dist: seaborn (>=0.11.2)
Requires-Dist: setuptools (~=58.0.4)
Requires-Dist: scipy (~=1.9.1)
